{
  "welcomeFile": "/webapp/index.html",
  "routes": [
    {
      "path": "/resources",
      "target": {
        "type": "service",
        "name": "sapui5",
        "entryPath": "/resources"
      },
      "description": "SAPUI5 Resources"
    },
    {
      "path": "/test-resources",
      "target": {
        "type": "service",
        "name": "sapui5",
        "entryPath": "/test-resources"
      },
      "description": "SAPUI5 Test Resources"
    },
     {
      "path": "/C4C-MY323481",
      "target": {
        "type": "destination",
        "name": "C4C-MY323481"
      },
      "description": "C4C DESTINATION"
    },
    {
      "path": "/C4C-MY323481-BASIC",
      "target": {
        "type": "destination",
        "name": "C4C-MY323481-BASIC"
      },
      "description": "C4C DESTINATION"
    },
    {
      "path": "/c4c-my500047",
      "target": {
        "type": "destination",
        "name": "c4c-my500047"
      },
      "description": "C4C DESTINATION"
    },
    {
      "path": "/SAP_CLOUD_EXT_SERVICE",
      "target": {
        "type": "destination",
        "name": "SAP_CLOUD_EXT_SERVICE"
      },
      "description": "C4C DESTINATION"
    }
  ],
  "sendWelcomeFileRedirect": true,
  "cacheControl": [
    {
      "directive": "private",
      "maxAge": 0,
      "path": "**.html"
    },
    {
      "directive": "private",
      "maxAge": 0,
      "path": "sap-ui-cachebuster-info.json"
    },
    {
      "directive": "public",
      "maxAge": 31536000
    }
  ]
}